{
  "codigo": 309,
  "nome": "SERVIÇO SOCIAL",
  "sigla_centro": "CSE",
  "sigla_departamento": "DSS",
  "trimestral": false,
  "periodo_corrente": 20252,
  "codigos_curriculos": {
    "19911": 19911,
    "19991": 19991,
    "20132": 20132
  },
  "sigla_campus": "UFSC/FLO",
  "situacao": 0,
  "situacao_descricao": "regular",
  "num_vagas_total": 240,
  "num_vagas_primeiro_semestre": 0,
  "num_vagas_segundo_semestre": 0,
  "presencial": true,
  "turmas": {
    "DSS7105-04309 (20252)": {
      "codigo_disciplina": "DSS7105",
      "codigo_turma": "04309",
      "periodo": 20252,
      "fase": 4,
      "shortname": "DSS7105-04309 (20252)",
      "codigo_curso": 309,
      "situacao": 1,
      "descricao_situacao": "Normal",
      "nome_disciplina": "Oficina Preparação ao Estágio",
      "carga_horaria": 72,
      "num_aulas_semana": 4,
      "sigla_departamento": "DSS",
      "vagas_ofertadas": 40,
      "vagas_ocupadas": 3,
      "vagas_ocupadas_isolada": 0,
      "saldo_vagas": 37,
      "reservada_curso": 0,
      "sequenciais_horas_ocupadas": {
        "66": 66,
        "67": 67,
        "68": 68,
        "69": 69
      }
    },
    "DSS7106-06309 (20252)": {
      "codigo_disciplina": "DSS7106",
      "codigo_turma": "06309",
      "periodo": 20252,
      "fase": 6,
      "shortname": "DSS7106-06309 (20252)",
      "codigo_curso": 309,
      "situacao": 1,
      "descricao_situacao": "Normal",
      "nome_disciplina": "Oficina Análise Institucional e Serviço Social",
      "carga_horaria": 72,
      "num_aulas_semana": 4,
      "sigla_departamento": "DSS",
      "vagas_ofertadas": 40,
      "vagas_ocupadas": 21,
      "vagas_ocupadas_isolada": 0,
      "saldo_vagas": 19,
      "reservada_curso": 0,
      "sequenciais_horas_ocupadas": {
        "18": 18,
        "19": 19,
        "20": 20,
        "21": 21
      }
    },
    "DSS7111-04309 (20252)": {
      "codigo_disciplina": "DSS7111",
      "codigo_turma": "04309",
      "periodo": 20252,
      "fase": 4,
      "shortname": "DSS7111-04309 (20252)",
      "codigo_curso": 309,
      "situacao": 1,
      "descricao_situacao": "Normal",
      "nome_disciplina": "FHTM SSII",
      "carga_horaria": 72,
      "num_aulas_semana": 4,
      "sigla_departamento": "DSS",
      "vagas_ofertadas": 40,
      "vagas_ocupadas": 5,
      "vagas_ocupadas_isolada": 0,
      "saldo_vagas": 35,
      "reservada_curso": 0,
      "sequenciais_horas_ocupadas": {
        "34": 34,
        "35": 35,
        "36": 36,
        "37": 37
      }
    },
    "DSS7112-05309 (20252)": {
      "codigo_disciplina": "DSS7112",
      "codigo_turma": "05309",
      "periodo": 20252,
      "fase": 5,
      "shortname": "DSS7112-05309 (20252)",
      "codigo_curso": 309,
      "situacao": 1,
      "descricao_situacao": "Normal",
      "nome_disciplina": "FHTM SS III",
      "carga_horaria": 72,
      "num_aulas_semana": 4,
      "sigla_departamento": "DSS",
      "vagas_ofertadas": 40,
      "vagas_ocupadas": 23,
      "vagas_ocupadas_isolada": 0,
      "saldo_vagas": 17,
      "reservada_curso": 0,
      "sequenciais_horas_ocupadas": {
        "18": 18,
        "19": 19,
        "20": 20,
        "21": 21
      }
    },
    "DSS7115-04309 (20252)": {
      "codigo_disciplina": "DSS7115",
      "codigo_turma": "04309",
      "periodo": 20252,
      "fase": 4,
      "shortname": "DSS7115-04309 (20252)",
      "codigo_curso": 309,
      "situacao": 1,
      "descricao_situacao": "Normal",
      "nome_disciplina": "Método Crítico Dialético",
      "carga_horaria": 72,
      "num_aulas_semana": 4,
      "sigla_departamento": "DSS",
      "vagas_ofertadas": 40,
      "vagas_ocupadas": 13,
      "vagas_ocupadas_isolada": 0,
      "saldo_vagas": 27,
      "reservada_curso": 0,
      "sequenciais_horas_ocupadas": {
        "2": 2,
        "3": 3,
        "4": 4,
        "5": 5
      }
    },
    "DSS7117-05309 (20252)": {
      "codigo_disciplina": "DSS7117",
      "codigo_turma": "05309",
      "periodo": 20252,
      "fase": 5,
      "shortname": "DSS7117-05309 (20252)",
      "codigo_curso": 309,
      "situacao": 1,
      "descricao_situacao": "Normal",
      "nome_disciplina": "Ética Profissional do Serviço Social",
      "carga_horaria": 72,
      "num_aulas_semana": 4,
      "sigla_departamento": "DSS",
      "vagas_ofertadas": 40,
      "vagas_ocupadas": 23,
      "vagas_ocupadas_isolada": 0,
      "saldo_vagas": 17,
      "reservada_curso": 0,
      "sequenciais_horas_ocupadas": {
        "34": 34,
        "35": 35,
        "36": 36,
        "37": 37
      }
    },
    "DSS7118-05309 (20252)": {
      "codigo_disciplina": "DSS7118",
      "codigo_turma": "05309",
      "periodo": 20252,
      "fase": 5,
      "shortname": "DSS7118-05309 (20252)",
      "codigo_curso": 309,
      "situacao": 1,
      "descricao_situacao": "Normal",
      "nome_disciplina": "Instrumentalidade e Competências Profissionais em Serviço Social",
      "carga_horaria": 72,
      "num_aulas_semana": 4,
      "sigla_departamento": "DSS",
      "vagas_ofertadas": 40,
      "vagas_ocupadas": 23,
      "vagas_ocupadas_isolada": 0,
      "saldo_vagas": 17,
      "reservada_curso": 0,
      "sequenciais_horas_ocupadas": {
        "66": 66,
        "67": 67,
        "68": 68,
        "69": 69
      }
    },
    "DSS7121-04309 (20252)": {
      "codigo_disciplina": "DSS7121",
      "codigo_turma": "04309",
      "periodo": 20252,
      "fase": 4,
      "shortname": "DSS7121-04309 (20252)",
      "codigo_curso": 309,
      "situacao": 1,
      "descricao_situacao": "Normal",
      "nome_disciplina": "Política Social",
      "carga_horaria": 72,
      "num_aulas_semana": 4,
      "sigla_departamento": "DSS",
      "vagas_ofertadas": 40,
      "vagas_ocupadas": 8,
      "vagas_ocupadas_isolada": 0,
      "saldo_vagas": 32,
      "reservada_curso": 0,
      "sequenciais_horas_ocupadas": {
        "18": 18,
        "19": 19,
        "20": 20,
        "21": 21
      }
    },
    "DSS7122-05309 (20252)": {
      "codigo_disciplina": "DSS7122",
      "codigo_turma": "05309",
      "periodo": 20252,
      "fase": 5,
      "shortname": "DSS7122-05309 (20252)",
      "codigo_curso": 309,
      "situacao": 1,
      "descricao_situacao": "Normal",
      "nome_disciplina": "Serviço Social e Previdência Social",
      "carga_horaria": 72,
      "num_aulas_semana": 4,
      "sigla_departamento": "DSS",
      "vagas_ofertadas": 40,
      "vagas_ocupadas": 28,
      "vagas_ocupadas_isolada": 0,
      "saldo_vagas": 12,
      "reservada_curso": 0,
      "sequenciais_horas_ocupadas": {
        "50": 50,
        "51": 51,
        "52": 52,
        "53": 53
      }
    },
    "DSS7123-06309 (20252)": {
      "codigo_disciplina": "DSS7123",
      "codigo_turma": "06309",
      "periodo": 20252,
      "fase": 6,
      "shortname": "DSS7123-06309 (20252)",
      "codigo_curso": 309,
      "situacao": 1,
      "descricao_situacao": "Normal",
      "nome_disciplina": "Serviço social e Assistência Social",
      "carga_horaria": 72,
      "num_aulas_semana": 4,
      "sigla_departamento": "DSS",
      "vagas_ofertadas": 40,
      "vagas_ocupadas": 21,
      "vagas_ocupadas_isolada": 1,
      "saldo_vagas": 18,
      "reservada_curso": 0,
      "sequenciais_horas_ocupadas": {
        "34": 34,
        "35": 35,
        "36": 36,
        "37": 37
      }
    },
    "DSS7124-07309 (20252)": {
      "codigo_disciplina": "DSS7124",
      "codigo_turma": "07309",
      "periodo": 20252,
      "fase": 7,
      "shortname": "DSS7124-07309 (20252)",
      "codigo_curso": 309,
      "situacao": 1,
      "descricao_situacao": "Normal",
      "nome_disciplina": "Serviço Social e Saúde",
      "carga_horaria": 72,
      "num_aulas_semana": 4,
      "sigla_departamento": "DSS",
      "vagas_ofertadas": 40,
      "vagas_ocupadas": 8,
      "vagas_ocupadas_isolada": 1,
      "saldo_vagas": 31,
      "reservada_curso": 0,
      "sequenciais_horas_ocupadas": {
        "50": 50,
        "51": 51,
        "52": 52,
        "53": 53
      }
    },
    "DSS7125-06309 (20252)": {
      "codigo_disciplina": "DSS7125",
      "codigo_turma": "06309",
      "periodo": 20252,
      "fase": 6,
      "shortname": "DSS7125-06309 (20252)",
      "codigo_curso": 309,
      "situacao": 1,
      "descricao_situacao": "Normal",
      "nome_disciplina": "Pesquisa em Serviço social I",
      "carga_horaria": 72,
      "num_aulas_semana": 4,
      "sigla_departamento": "DSS",
      "vagas_ofertadas": 40,
      "vagas_ocupadas": 23,
      "vagas_ocupadas_isolada": 0,
      "saldo_vagas": 17,
      "reservada_curso": 0,
      "sequenciais_horas_ocupadas": {
        "50": 50,
        "51": 51,
        "52": 52,
        "53": 53
      }
    },
    "DSS7126-07309 (20252)": {
      "codigo_disciplina": "DSS7126",
      "codigo_turma": "07309",
      "periodo": 20252,
      "fase": 7,
      "shortname": "DSS7126-07309 (20252)",
      "codigo_curso": 309,
      "situacao": 1,
      "descricao_situacao": "Normal",
      "nome_disciplina": "Pesquisa em Serviço Social II",
      "carga_horaria": 72,
      "num_aulas_semana": 4,
      "sigla_departamento": "DSS",
      "vagas_ofertadas": 40,
      "vagas_ocupadas": 16,
      "vagas_ocupadas_isolada": 0,
      "saldo_vagas": 24,
      "reservada_curso": 0,
      "sequenciais_horas_ocupadas": {
        "34": 34,
        "35": 35,
        "36": 36,
        "37": 37
      }
    },
    "DSS7127-07309 (20252)": {
      "codigo_disciplina": "DSS7127",
      "codigo_turma": "07309",
      "periodo": 20252,
      "fase": 7,
      "shortname": "DSS7127-07309 (20252)",
      "codigo_curso": 309,
      "situacao": 1,
      "descricao_situacao": "Normal",
      "nome_disciplina": "Gestão e Planejamento em serviço Social I",
      "carga_horaria": 72,
      "num_aulas_semana": 4,
      "sigla_departamento": "DSS",
      "vagas_ofertadas": 40,
      "vagas_ocupadas": 12,
      "vagas_ocupadas_isolada": 0,
      "saldo_vagas": 28,
      "reservada_curso": 0,
      "sequenciais_horas_ocupadas": {
        "66": 66,
        "67": 67,
        "68": 68,
        "69": 69
      }
    },
    "DSS7128-08309 (20252)": {
      "codigo_disciplina": "DSS7128",
      "codigo_turma": "08309",
      "periodo": 20252,
      "fase": 8,
      "shortname": "DSS7128-08309 (20252)",
      "codigo_curso": 309,
      "situacao": 1,
      "descricao_situacao": "Normal",
      "nome_disciplina": "Gestão e Planejamento em serviço Social II",
      "carga_horaria": 72,
      "num_aulas_semana": 4,
      "sigla_departamento": "DSS",
      "vagas_ofertadas": 40,
      "vagas_ocupadas": 15,
      "vagas_ocupadas_isolada": 0,
      "saldo_vagas": 25,
      "reservada_curso": 0,
      "sequenciais_horas_ocupadas": {
        "18": 18,
        "19": 19,
        "20": 20,
        "21": 21
      }
    },
    "DSS7131-06309 (20252)": {
      "codigo_disciplina": "DSS7131",
      "codigo_turma": "06309",
      "periodo": 20252,
      "fase": 6,
      "shortname": "DSS7131-06309 (20252)",
      "codigo_curso": 309,
      "situacao": 1,
      "descricao_situacao": "Normal",
      "nome_disciplina": "Supervisão Acadêmica de Estágio Obrigatório I",
      "carga_horaria": 72,
      "num_aulas_semana": 4,
      "sigla_departamento": "DSS",
      "vagas_ofertadas": 36,
      "vagas_ocupadas": 15,
      "vagas_ocupadas_isolada": 0,
      "saldo_vagas": 21,
      "reservada_curso": 0,
      "sequenciais_horas_ocupadas": {
        "2": 2,
        "3": 3,
        "4": 4,
        "5": 5
      }
    },
    "DSS7132-07309 (20252)": {
      "codigo_disciplina": "DSS7132",
      "codigo_turma": "07309",
      "periodo": 20252,
      "fase": 7,
      "shortname": "DSS7132-07309 (20252)",
      "codigo_curso": 309,
      "situacao": 1,
      "descricao_situacao": "Normal",
      "nome_disciplina": "Supervisão Acadêmica de Estágio Obrigatório II",
      "carga_horaria": 72,
      "num_aulas_semana": 4,
      "sigla_departamento": "DSS",
      "vagas_ofertadas": 15,
      "vagas_ocupadas": 8,
      "vagas_ocupadas_isolada": 0,
      "saldo_vagas": 7,
      "reservada_curso": 0,
      "sequenciais_horas_ocupadas": {
        "2": 2,
        "3": 3,
        "4": 4,
        "5": 5
      }
    },
    "DSS7133-08309 (20252)": {
      "codigo_disciplina": "DSS7133",
      "codigo_turma": "08309",
      "periodo": 20252,
      "fase": 8,
      "shortname": "DSS7133-08309 (20252)",
      "codigo_curso": 309,
      "situacao": 1,
      "descricao_situacao": "Normal",
      "nome_disciplina": "Supervisão Acadêmica de Estágio Obrigatório III",
      "carga_horaria": 72,
      "num_aulas_semana": 4,
      "sigla_departamento": "DSS",
      "vagas_ofertadas": 16,
      "vagas_ocupadas": 7,
      "vagas_ocupadas_isolada": 0,
      "saldo_vagas": 9,
      "reservada_curso": 0,
      "sequenciais_horas_ocupadas": {
        "2": 2,
        "3": 3,
        "4": 4,
        "5": 5
      }
    },
    "DSS7141-06309 (20252)": {
      "codigo_disciplina": "DSS7141",
      "codigo_turma": "06309",
      "periodo": 20252,
      "fase": 6,
      "shortname": "DSS7141-06309 (20252)",
      "codigo_curso": 309,
      "situacao": 1,
      "descricao_situacao": "Normal",
      "nome_disciplina": "Estágio Supervisionado em Serviço Social Obrigatório I",
      "carga_horaria": 216,
      "num_aulas_semana": 12,
      "sigla_departamento": "DSS",
      "vagas_ofertadas": 15,
      "vagas_ocupadas": 15,
      "vagas_ocupadas_isolada": 0,
      "saldo_vagas": 0,
      "reservada_curso": 0,
      "sequenciais_horas_ocupadas": []
    },
    "DSS7142-07309 (20252)": {
      "codigo_disciplina": "DSS7142",
      "codigo_turma": "07309",
      "periodo": 20252,
      "fase": 7,
      "shortname": "DSS7142-07309 (20252)",
      "codigo_curso": 309,
      "situacao": 1,
      "descricao_situacao": "Normal",
      "nome_disciplina": "Estágio Superv.em Serv. Social Obrigatório II",
      "carga_horaria": 216,
      "num_aulas_semana": 12,
      "sigla_departamento": "DSS",
      "vagas_ofertadas": 15,
      "vagas_ocupadas": 8,
      "vagas_ocupadas_isolada": 0,
      "saldo_vagas": 7,
      "reservada_curso": 0,
      "sequenciais_horas_ocupadas": []
    },
    "DSS7143-08309 (20252)": {
      "codigo_disciplina": "DSS7143",
      "codigo_turma": "08309",
      "periodo": 20252,
      "fase": 8,
      "shortname": "DSS7143-08309 (20252)",
      "codigo_curso": 309,
      "situacao": 1,
      "descricao_situacao": "Normal",
      "nome_disciplina": "Estágio Supervisionado em serviço Social Obrigatório III",
      "carga_horaria": 180,
      "num_aulas_semana": 10,
      "sigla_departamento": "DSS",
      "vagas_ofertadas": 16,
      "vagas_ocupadas": 7,
      "vagas_ocupadas_isolada": 0,
      "saldo_vagas": 9,
      "reservada_curso": 0,
      "sequenciais_horas_ocupadas": []
    },
    "DSS7151-08309 (20252)": {
      "codigo_disciplina": "DSS7151",
      "codigo_turma": "08309",
      "periodo": 20252,
      "fase": 8,
      "shortname": "DSS7151-08309 (20252)",
      "codigo_curso": 309,
      "situacao": 1,
      "descricao_situacao": "Normal",
      "nome_disciplina": "Trabalho de conclusão de Curso I",
      "carga_horaria": 36,
      "num_aulas_semana": 2,
      "sigla_departamento": "DSS",
      "vagas_ofertadas": 40,
      "vagas_ocupadas": 12,
      "vagas_ocupadas_isolada": 0,
      "saldo_vagas": 28,
      "reservada_curso": 0,
      "sequenciais_horas_ocupadas": {
        "50": 50,
        "51": 51
      }
    },
    "DSS7152-09309 (20252)": {
      "codigo_disciplina": "DSS7152",
      "codigo_turma": "09309",
      "periodo": 20252,
      "fase": 9,
      "shortname": "DSS7152-09309 (20252)",
      "codigo_curso": 309,
      "situacao": 1,
      "descricao_situacao": "Normal",
      "nome_disciplina": "Trabalho de Conclusão de Curso II",
      "carga_horaria": 108,
      "num_aulas_semana": 6,
      "sigla_departamento": "DSS",
      "vagas_ofertadas": 40,
      "vagas_ocupadas": 32,
      "vagas_ocupadas_isolada": 0,
      "saldo_vagas": 8,
      "reservada_curso": 0,
      "sequenciais_horas_ocupadas": {
        "66": 66,
        "67": 67
      }
    },
    "DSS7153-09309 (20252)": {
      "codigo_disciplina": "DSS7153",
      "codigo_turma": "09309",
      "periodo": 20252,
      "fase": 9,
      "shortname": "DSS7153-09309 (20252)",
      "codigo_curso": 309,
      "situacao": 1,
      "descricao_situacao": "Normal",
      "nome_disciplina": "Serviço Social e Desafios Profissionais Contemporâneos",
      "carga_horaria": 72,
      "num_aulas_semana": 4,
      "sigla_departamento": "DSS",
      "vagas_ofertadas": 40,
      "vagas_ocupadas": 10,
      "vagas_ocupadas_isolada": 0,
      "saldo_vagas": 30,
      "reservada_curso": 0,
      "sequenciais_horas_ocupadas": {
        "34": 34,
        "35": 35,
        "36": 36,
        "37": 37
      }
    },
    "DSS7165-09309 (20252)": {
      "codigo_disciplina": "DSS7165",
      "codigo_turma": "09309",
      "periodo": 20252,
      "fase": 9,
      "shortname": "DSS7165-09309 (20252)",
      "codigo_curso": 309,
      "situacao": 1,
      "descricao_situacao": "Normal",
      "nome_disciplina": "Serviço Social e Envelhecimento",
      "carga_horaria": 72,
      "num_aulas_semana": 4,
      "sigla_departamento": "DSS",
      "vagas_ofertadas": 35,
      "vagas_ocupadas": 31,
      "vagas_ocupadas_isolada": 0,
      "saldo_vagas": 4,
      "reservada_curso": 0,
      "sequenciais_horas_ocupadas": {
        "18": 18,
        "19": 19,
        "20": 20,
        "21": 21
      }
    },
    "FIL7100-04309 (20252)": {
      "codigo_disciplina": "FIL7100",
      "codigo_turma": "04309",
      "periodo": 20252,
      "fase": 4,
      "shortname": "FIL7100-04309 (20252)",
      "codigo_curso": 309,
      "situacao": 1,
      "descricao_situacao": "Normal",
      "nome_disciplina": "Introdução a Ética",
      "carga_horaria": 72,
      "num_aulas_semana": 4,
      "sigla_departamento": "FIL",
      "vagas_ofertadas": 40,
      "vagas_ocupadas": 5,
      "vagas_ocupadas_isolada": 1,
      "saldo_vagas": 34,
      "reservada_curso": 0,
      "sequenciais_horas_ocupadas": {
        "50": 50,
        "51": 51,
        "52": 52,
        "53": 53
      }
    }
  }
}